sphinx_autorun/__init__.py
sphinx_autorun/pycon.py
sphinx_autorun/version.py
sphinx_autorun-2.0.0.dist-info/AUTHORS
sphinx_autorun-2.0.0.dist-info/LICENCE
sphinx_autorun-2.0.0.dist-info/METADATA
sphinx_autorun-2.0.0.dist-info/WHEEL
sphinx_autorun-2.0.0.dist-info/top_level.txt
sphinx_autorun-2.0.0.dist-info/RECORD
