Metadata-Version: 2.1
Name: sphinx-autorun
Version: 2.0.0
Summary: Sphinx extension autorun
Author-email: Hugo Osvaldo Barrera <hugo@whynothugo.nl>
License: BSD-2-Clause
Project-URL: homepage, https://github.com/WhyNotHugo/sphinx-autorun
Project-URL: download_url, http://pypi.python.org/pypi/sphinx-autorun
Classifier: Development Status :: 4 - Beta
Classifier: Environment :: Console
Classifier: Environment :: Web Environment
Classifier: Intended Audience :: Developers
Classifier: License :: OSI Approved :: BSD License
Classifier: Operating System :: OS Independent
Classifier: Programming Language :: Python :: 3
Classifier: Programming Language :: Python :: 3.9
Classifier: Programming Language :: Python :: 3.10
Classifier: Programming Language :: Python :: 3.11
Classifier: Programming Language :: Python :: 3.12
Classifier: Programming Language :: Python :: 3.13
Classifier: Topic :: Documentation
Classifier: Topic :: Utilities
Requires-Python: >=3.9
License-File: LICENCE
License-File: AUTHORS
Requires-Dist: Sphinx>=0.6
